byteit/ByteITClient.py
byteit/__init__.py
byteit/exceptions.py
byteit/progress.py
byteit/validations.py
byteit/connectors/LocalFileInputConnector.py
byteit/connectors/LocalFileOutputConnector.py
byteit/connectors/S3InputConnector.py
byteit/connectors/S3OutputConnector.py
byteit/connectors/__init__.py
byteit/connectors/base.py
byteit/models/DocumentMetadata.py
byteit/models/Job.py
byteit/models/JobList.py
byteit/models/OutputFormat.py
byteit/models/ProcessingOptions.py
byteit-0.1.2.dist-info/LICENSE
byteit-0.1.2.dist-info/METADATA
byteit-0.1.2.dist-info/WHEEL
byteit-0.1.2.dist-info/top_level.txt
byteit-0.1.2.dist-info/RECORD
