Metadata-Version: 2.1
Name: byteit
Version: 0.1.2
Summary: AI-powered document intelligence platform - Turn your data into structured data with a single line of code.
Author-email: ByteIT GmbH <support@byteit.ai>
License: Apache-2.0
Project-URL: Homepage, https://byteit.ai
Project-URL: Repository, https://github.com/byteit-ai/byteit-api
Project-URL: Pricing, https://byteit.ai/pricing
Project-URL: Support, https://byteit.ai/support
Project-URL: Contact, https://byteit.ai/contact
Keywords: document-processing,ai,document-intelligence,pdf,data-extraction,machine-learning,ocr
Classifier: Development Status :: 4 - Beta
Classifier: Intended Audience :: Developers
Classifier: License :: OSI Approved :: Apache Software License
Classifier: Operating System :: OS Independent
Classifier: Programming Language :: Python
Classifier: Programming Language :: Python :: 3
Classifier: Programming Language :: Python :: 3.8
Classifier: Programming Language :: Python :: 3.9
Classifier: Programming Language :: Python :: 3.10
Classifier: Programming Language :: Python :: 3.11
Classifier: Programming Language :: Python :: 3.12
Classifier: Topic :: Software Development :: Libraries :: Python Modules
Classifier: Topic :: Office/Business
Requires-Python: >=3.8
License-File: LICENSE
Requires-Dist: requests>=2.28.0
Requires-Dist: tqdm>=4.65.0
Provides-Extra: dev
Requires-Dist: pytest>=7.0.0; extra == "dev"
Requires-Dist: pytest-cov>=4.0.0; extra == "dev"
Requires-Dist: black>=23.0.0; extra == "dev"
Requires-Dist: isort>=5.0.0; extra == "dev"
Requires-Dist: flake8>=6.0.0; extra == "dev"
Requires-Dist: mypy>=1.0.0; extra == "dev"
